shortenIt/__init__.py
shortenIt/bot.py
shortenIt-0.0.3.dist-info/METADATA
shortenIt-0.0.3.dist-info/WHEEL
shortenIt-0.0.3.dist-info/top_level.txt
shortenIt-0.0.3.dist-info/RECORD
