Metadata-Version: 2.1
Name: shortenIt
Version: 0.0.3
Summary: Package for summarizing Text 
Home-page: https://github.com/Jash271/SummarizeIt
Author: Jash Shah
Author-email: shahjash271@gmail.com
License: MIT
Platform: UNKNOWN
Classifier: Development Status :: 4 - Beta
Classifier: License :: OSI Approved :: MIT License
Classifier: Programming Language :: Python
Classifier: Topic :: Software Development :: Libraries
Classifier: Topic :: Software Development :: Libraries :: Python Modules
Classifier: Intended Audience :: Developers
Requires-Python: >=3.6.8
Requires-Dist: nltk
